grpc_cotea/__init__.py
grpc_cotea/ansible_execution_config.py
grpc_cotea/cotea_gateway.py
grpc_cotea/cotea_gateway_server.py
grpc_cotea/cotea_pb2.py
grpc_cotea/cotea_pb2_grpc.py
grpc_cotea/cotea_worker.py
grpc_cotea/cotea_worker_server.py
grpc_cotea/cotea_worker_spawner.py
grpc_cotea/grpc_cotea_exception.py
grpc_cotea/grpc_server.py
grpc_cotea/start_tmpl.j2
grpc_cotea/utils.py
grpc_cotea/worker_connecter.py
grpc_cotea/worker_maker.py
grpc_cotea/ansible_mitogen/__init__.py
grpc_cotea/ansible_mitogen/affinity.py
grpc_cotea/ansible_mitogen/connection.py
grpc_cotea/ansible_mitogen/loaders.py
grpc_cotea/ansible_mitogen/logging.py
grpc_cotea/ansible_mitogen/mixins.py
grpc_cotea/ansible_mitogen/module_finder.py
grpc_cotea/ansible_mitogen/parsing.py
grpc_cotea/ansible_mitogen/planner.py
grpc_cotea/ansible_mitogen/process.py
grpc_cotea/ansible_mitogen/runner.py
grpc_cotea/ansible_mitogen/services.py
grpc_cotea/ansible_mitogen/strategy.py
grpc_cotea/ansible_mitogen/target.py
grpc_cotea/ansible_mitogen/transport_config.py
grpc_cotea/ansible_mitogen/utils.py
grpc_cotea/ansible_mitogen/compat/__init__.py
grpc_cotea/ansible_mitogen/plugins/__init__.py
grpc_cotea/ansible_mitogen/plugins/action/__init__.py
grpc_cotea/ansible_mitogen/plugins/action/mitogen_fetch.py
grpc_cotea/ansible_mitogen/plugins/action/mitogen_get_stack.py
grpc_cotea/ansible_mitogen/plugins/connection/__init__.py
grpc_cotea/ansible_mitogen/plugins/connection/mitogen_buildah.py
grpc_cotea/ansible_mitogen/plugins/connection/mitogen_doas.py
grpc_cotea/ansible_mitogen/plugins/connection/mitogen_docker.py
grpc_cotea/ansible_mitogen/plugins/connection/mitogen_jail.py
grpc_cotea/ansible_mitogen/plugins/connection/mitogen_kubectl.py
grpc_cotea/ansible_mitogen/plugins/connection/mitogen_local.py
grpc_cotea/ansible_mitogen/plugins/connection/mitogen_lxc.py
grpc_cotea/ansible_mitogen/plugins/connection/mitogen_lxd.py
grpc_cotea/ansible_mitogen/plugins/connection/mitogen_machinectl.py
grpc_cotea-0.9.25.dist-info/LICENSE.md
grpc_cotea-0.9.25.dist-info/METADATA
grpc_cotea-0.9.25.dist-info/WHEEL
grpc_cotea-0.9.25.dist-info/entry_points.txt
grpc_cotea-0.9.25.dist-info/top_level.txt
grpc_cotea-0.9.25.dist-info/RECORD
